BrainConnect/__init__.py
BrainConnect/__main__.py
BrainConnect/data_fusion.py
BrainConnect/feature_integrator.py
BrainConnect/model.py
BrainConnect/swc_processor.py
brainconnect-1.0.0.dist-info/licenses/LICENSE
brainconnect-1.0.0.dist-info/METADATA
brainconnect-1.0.0.dist-info/WHEEL
brainconnect-1.0.0.dist-info/entry_points.txt
brainconnect-1.0.0.dist-info/top_level.txt
brainconnect-1.0.0.dist-info/RECORD
