Metadata-Version: 2.4
Name: BrainConnect
Version: 1.0.0
Summary: A flexible pipeline to integrate brain connectivity and spatial transcriptomics for downstream analysis
Author-email: CPenglab <chengpeng@ynu.edu.cn>, sparkumr <1984607077@qq.com>
Maintainer-email: sparkumr <1984607077@qq.com>
License: GPLv3
Project-URL: Repository, https://github.com/CPenglab/BrainConnect
Keywords: Neuron,Allen,Model,Spatial Transcriptomics
Classifier: Development Status :: 4 - Beta
Classifier: Environment :: Console
Classifier: License :: OSI Approved :: GNU General Public License v3 (GPLv3)
Classifier: Operating System :: OS Independent
Classifier: Programming Language :: Python :: 3 :: Only
Classifier: Topic :: Scientific/Engineering :: Bio-Informatics
Requires-Python: >=3.12
License-File: LICENSE
Requires-Dist: pandas==2.2.3
Requires-Dist: numpy==2.2.4
Requires-Dist: tqdm==4.67.1
Requires-Dist: pyswcloader==1.1.1
Requires-Dist: pynrrd==1.1.3
Requires-Dist: networkx==3.5
Requires-Dist: tensorflow==2.20.0
Dynamic: license-file
